<problem linenum="809" tex_filename="./week3_4_ps2a.tex" attempts="10" display_name="Stabilizer description of quantum circuit transformations" max_attempts="10">
  <script>
import qpython4
qpython4.define_qpython4_globals(globals())


</script>
  <p>
Consider the following simple quantum circuit: </p>
  <p>
    <center>
      <img src="/static/images/bell-circuit-stab-v2.png" width="300"/>
    </center>
  </p>
  <p>
The input state is [mathjaxinline]|00\rangle[/mathjaxinline], which is stabilized by [mathjaxinline]{\cal S}_0 = \langle {\tt IZ},{\tt ZI}\rangle[/mathjaxinline]. Give the stabilizers describing the state after the Hadamard and after the controlled-NOT gate. </p>
  <p>
Work this out by using the fact that [mathjaxinline]U[/mathjaxinline] acting on a state stabilized by [mathjaxinline]{\cal S}[/mathjaxinline] produces a state stabilized by [mathjaxinline]U{\cal S}U^\dagger[/mathjaxinline]. </p>
  <p>
You can also double-check yourself by working out the explicit quantum states produced in the circuit, and figuring out the stabilizers for each of the states. However, for circuits composed of <em>Clifford group</em> gates, namely circuits generated by [mathjaxinline]H[/mathjaxinline], [mathjaxinline]S[/mathjaxinline], and the controlled-NOT gate, it is much faster to work directly with the stabilizer. </p>
  <p>
Enter each stabilizer as a list of generators, eg <tt class="tt">[IX,XI]</tt>: </p>
  <ul class="itemize">
    <li>
      <p>
        <p style="display:inline">[mathjaxinline]{\cal S_1} = ~[/mathjaxinline]: </p>
        <customresponse cfn="check_stabilizer_equality" inline="1" expect="[IZ,XI]">
          <textline size="20" correct_answer="[IZ,XI]" inline="1"/>
        </customresponse>
      </p>
    </li>
    <li>
      <p>
        <p style="display:inline">[mathjaxinline]{\cal S_2} = ~[/mathjaxinline]: </p>
        <customresponse cfn="check_stabilizer_equality" inline="1" expect="[ZZ,XX]">
          <textline size="20" correct_answer="[ZZ,XX]" inline="1"/>
        </customresponse>
      </p>
    </li>
  </ul>
</problem>
